django_s3_csv_2_sfdc/__init__.py
django_s3_csv_2_sfdc/csv_helpers.py
django_s3_csv_2_sfdc/orchestrator.py
django_s3_csv_2_sfdc/s3_helpers.py
django_s3_csv_2_sfdc/salesforce_client.py
django_s3_csv_2_sfdc/sfdc_helpers.py
django_s3_csv_2_sfdc/step_function_helpers.py
django_s3_csv_2_sfdc/utils.py
django_s3_csv_2_sfdc-0.4.6.dist-info/WHEEL
django_s3_csv_2_sfdc-0.4.6.dist-info/METADATA
django_s3_csv_2_sfdc-0.4.6.dist-info/RECORD
